README.md
setup.cfg
setup.py
distributions_asif/Binomialdistribution.py
distributions_asif/Gaussiandistribution.py
distributions_asif/Generaldistribution.py
distributions_asif/__init__.py
distributions_asif.egg-info/PKG-INFO
distributions_asif.egg-info/SOURCES.txt
distributions_asif.egg-info/dependency_links.txt
distributions_asif.egg-info/not-zip-safe
distributions_asif.egg-info/top_level.txt